.clang-format
.gitignore
.gitmodules
CMakeLists.txt
LICENSE
MANIFEST.in
README.rst
codecov.yml
pyproject.toml
readthedocs.yml
setup.cfg
setup.py
.github/workflows/deploy.yml
.github/workflows/deploy_test.yml
.github/workflows/test-package-windows.yml
.github/workflows/test-package.yml
affine_transform/__init__.py
affine_transform/affine_transform.py
affine_transform/version.txt
affine_transform.egg-info/PKG-INFO
affine_transform.egg-info/SOURCES.txt
affine_transform.egg-info/dependency_links.txt
affine_transform.egg-info/not-zip-safe
affine_transform.egg-info/requires.txt
affine_transform.egg-info/top_level.txt
docs/conf.py
docs/cpp_doc.rst
docs/how_to_use.rst
docs/index.rst
docs/make.bat
docs/module_doc.rst
docs/requirements.txt
docs/cpp/.gitignore
docs/cpp/Doxyfile
docs/cpp_docs/affine_transform.rst
docs/cpp_docs/apply_interpolation.rst
docs/cpp_docs/constant_boundary.rst
docs/cpp_docs/cubic_interpolation.rst
docs/cpp_docs/data_struct.rst
docs/cpp_docs/extract.rst
docs/cpp_docs/interpolation.rst
docs/cpp_docs/linear_interpolation.rst
docs/cpp_docs/python_bindings.rst
docs/cpp_docs/transform.rst
docs/cpp_docs/transform_loop.rst
examples/rotation_and_translation.py
extern/eigen/Eigen/Cholesky
extern/eigen/Eigen/CholmodSupport
extern/eigen/Eigen/Core
extern/eigen/Eigen/Dense
extern/eigen/Eigen/Eigen
extern/eigen/Eigen/Eigenvalues
extern/eigen/Eigen/Geometry
extern/eigen/Eigen/Householder
extern/eigen/Eigen/IterativeLinearSolvers
extern/eigen/Eigen/Jacobi
extern/eigen/Eigen/KLUSupport
extern/eigen/Eigen/LU
extern/eigen/Eigen/MetisSupport
extern/eigen/Eigen/OrderingMethods
extern/eigen/Eigen/PaStiXSupport
extern/eigen/Eigen/PardisoSupport
extern/eigen/Eigen/QR
extern/eigen/Eigen/QtAlignedMalloc
extern/eigen/Eigen/SPQRSupport
extern/eigen/Eigen/SVD
extern/eigen/Eigen/Sparse
extern/eigen/Eigen/SparseCholesky
extern/eigen/Eigen/SparseCore
extern/eigen/Eigen/SparseLU
extern/eigen/Eigen/SparseQR
extern/eigen/Eigen/StdDeque
extern/eigen/Eigen/StdList
extern/eigen/Eigen/StdVector
extern/eigen/Eigen/SuperLUSupport
extern/eigen/Eigen/UmfPackSupport
extern/eigen/Eigen/src/Cholesky/LDLT.h
extern/eigen/Eigen/src/Cholesky/LLT.h
extern/eigen/Eigen/src/Cholesky/LLT_LAPACKE.h
