Metadata-Version: 2.1
Name: affine-transform
Version: 0.3.2
Summary: Easy to use multi-core affine transformations
Home-page: https://github.com/NOhs/affine_transform_nd
Author: NOhs, TobelRunner
License: MIT
Classifier: Programming Language :: Python :: 3.8
Classifier: Programming Language :: Python :: 3.9
Classifier: Programming Language :: Python :: 3.10
Classifier: Programming Language :: Python :: 3.11
Classifier: Programming Language :: C++
Classifier: License :: OSI Approved :: MIT License
Requires-Python: >=3.8
License-File: LICENSE
